Metadata-Version: 2.1
Name: method-defaults
Version: 1.0.1
Summary: Simple file based configuration to supply default parameters to any method
Home-page: https://gitlab.com/maartincm/method_defaults
Author: Martín Nicolás Cuesta
Author-email: cuesta.martin.n@hotmail.com
Maintainer-email: cuesta.martin.n@hotmail.com
License: AGPL3+
Platform: UNKNOWN
Classifier: Intended Audience :: Developers
Classifier: Intended Audience :: Information Technology
Classifier: Programming Language :: Python :: 3
Classifier: Operating System :: OS Independent
